{"v":"5.4.2","fr":29.9700012207031,"ip":0,"op":60.0000024438501,"w":540,"h":540,"nm":"ExOut","ddd":1,"assets":[],"fonts":{"list":[{"fName":"ComicSansMS-Bold","fFamily":"Comic Sans MS","fStyle":"Bold","ascent":89.8546752929688}]},"layers":[{"ddd":1,"ind":1,"ty":5,"nm":"x","sr":1,"ks":{"o":{"a":1,"k":[{"i":{"x":[0.833],"y":[0.833]},"o":{"x":[0.167],"y":[0.167]},"n":["0p833_0p833_0p167_0p167"],"t":11,"s":[0],"e":[100]},{"t":12.00000048877}],"ix":11},"rx":{"a":0,"k":0,"ix":8},"ry":{"a":0,"k":0,"ix":9},"rz":{"a":0,"k":0,"ix":10},"or":{"a":0,"k":[0,0,0],"ix":7},"p":{"a":0,"k":[100,438,0],"ix":2},"a":{"a":0,"k":[0,0,0],"ix":1},"s":{"a":0,"k":[100,100,100],"ix":6}},"ao":0,"t":{"d":{"k":[{"s":{"s":594,"f":"ComicSansMS-Bold","t":"x","j":3,"tr":0,"lh":712.8,"ls":15,"fc":[1,1,1],"sc":[0,0,0],"sw":6,"of":true},"t":0}]},"p":{},"m":{"g":1,"a":{"a":0,"k":[0,0],"ix":2}},"a":[]},"ip":0,"op":60.0000024438501,"st":0,"bm":0},{"ddd":0,"ind":2,"ty":4,"nm":"Shape Layer 1","sr":1,"ks":{"o":{"a":1,"k":[{"i":{"x":[0.833],"y":[0.833]},"o":{"x":[0.167],"y":[0.167]},"n":["0p833_0p833_0p167_0p167"],"t":2,"s":[0],"e":[100]},{"t":7.00000028511585}],"ix":11},"r":{"a":0,"k":0,"ix":10},"p":{"a":0,"k":[270,270,0],"ix":2},"a":{"a":0,"k":[-25,-17,0],"ix":1},"s":{"a":1,"k":[{"i":{"x":[0.833,0.833,0.833],"y":[0.833,0.833,0.833]},"o":{"x":[0.167,0.167,0.167],"y":[0.167,0.167,0.167]},"n":["0p833_0p833_0p167_0p167","0p833_0p833_0p167_0p167","0p833_0p833_0p167_0p167"],"t":0,"s":[0,0,100],"e":[187,187,100]},{"i":{"x":[0.833,0.833,0.833],"y":[0.833,0.833,0.833]},"o":{"x":[0.167,0.167,0.167],"y":[0.167,0.167,0.167]},"n":["0p833_0p833_0p167_0p167","0p833_0p833_0p167_0p167","0p833_0p833_0p167_0p167"],"t":9,"s":[187,187,100],"e":[175,175,100]},{"t":11.0000004480392}],"ix":6}},"ao":0,"shapes":[{"ty":"gr","it":[{"d":1,"ty":"el","s":{"a":0,"k":[288,278],"ix":2},"p":{"a":0,"k":[0,0],"ix":3},"nm":"Ellipse Path 1","mn":"ADBE Vector Shape - Ellipse","hd":false},{"ty":"st","c":{"a":0,"k":[0.541176470588,0.01697808434,0.01697808434,1],"ix":3},"o":{"a":0,"k":100,"ix":4},"w":{"a":0,"k":12,"ix":5},"lc":1,"lj":1,"ml":4,"ml2":{"a":0,"k":4,"ix":8},"nm":"Stroke 1","mn":"ADBE Vector Graphic - Stroke","hd":false},{"ty":"fl","c":{"a":0,"k":[1,0,0,1],"ix":4},"o":{"a":0,"k":100,"ix":5},"r":1,"nm":"Fill 1","mn":"ADBE Vector Graphic - Fill","hd":false},{"ty":"tr","p":{"a":0,"k":[-24,-19],"ix":2},"a":{"a":0,"k":[0,0],"ix":1},"s":{"a":0,"k":[100,100],"ix":3},"r":{"a":0,"k":0,"ix":6},"o":{"a":0,"k":100,"ix":7},"sk":{"a":0,"k":0,"ix":4},"sa":{"a":0,"k":0,"ix":5},"nm":"Transform"}],"nm":"Ellipse 1","np":3,"cix":2,"ix":1,"mn":"ADBE Vector Group","hd":false}],"ip":0,"op":60.0000024438501,"st":0,"bm":0}],"markers":[],"chars":[{"ch":"x","size":594,"style":"Bold","w":59.03,"data":{"shapes":[{"ty":"gr","it":[{"ind":0,"ty":"sh","ix":1,"ks":{"a":0,"k":{"i":[[0,2.116],[1.383,1.237],[1.758,0],[1.399,-1.985],[3.45,-2.995],[2.799,-2.344],[0,0],[2.311,0],[1.286,-1.318],[0,-1.692],[-1.693,-1.399],[-2.246,-2.995],[-1.823,-2.539],[1.985,-1.985],[2.148,-1.855],[0,-1.888],[-1.351,-1.27],[-1.758,0],[-1.433,1.498],[-1.758,1.465],[-2.637,2.637],[-2.93,-3.19],[-1.823,0],[-1.367,1.27],[0,1.693],[1.074,1.335],[0,0],[0,0],[-1.855,1.595]],"o":[[0,-1.692],[-1.384,-1.237],[-2.148,0],[-1.498,2.116],[-2.767,2.344],[0,0],[-4.07,-4.655],[-1.791,0],[-1.286,1.318],[0,1.758],[1.985,1.66],[1.855,2.539],[-4.199,4.102],[-2.148,1.823],[-2.67,2.441],[0,1.693],[1.35,1.27],[1.79,0],[0.911,-0.977],[5.534,-5.045],[6.738,8.301],[1.432,1.563],[1.758,0],[1.367,-1.27],[0,-1.302],[0,0],[0,0],[2.93,-2.604],[3.385,-3.288]],"v":[[58.154,-47.705],[56.079,-52.1],[51.367,-53.955],[46.045,-50.977],[38.623,-43.311],[30.273,-36.279],[22.461,-46.338],[12.891,-53.32],[8.276,-51.343],[6.348,-46.826],[8.887,-42.09],[15.234,-35.107],[20.752,-27.49],[11.475,-18.359],[5.029,-12.842],[1.025,-6.348],[3.052,-1.904],[7.715,0],[12.549,-2.246],[16.553,-5.908],[28.809,-17.432],[43.311,-0.195],[48.193,2.148],[52.881,0.244],[54.932,-4.199],[53.32,-8.154],[38.428,-26.367],[45.898,-33.301],[53.076,-39.6]],"c":true},"ix":2},"nm":"x","mn":"ADBE Vector Shape - Group","hd":false}],"nm":"x","np":3,"cix":2,"ix":1,"mn":"ADBE Vector Group","hd":false}]},"fFamily":"Comic Sans MS"}]}